causalscbench/__init__.py
causalscbench/apps/__init__.py
causalscbench/apps/evaluation_app.py
causalscbench/apps/main_app.py
causalscbench/apps/utils/__init__.py
causalscbench/apps/utils/run_utils.py
causalscbench/data_access/__init__.py
causalscbench/data_access/create_dataset.py
causalscbench/data_access/create_evaluation_datasets.py
causalscbench/data_access/create_name_to_ensembl_map.py
causalscbench/data_access/data/Hep_G2_ChipSeq.csv
causalscbench/data_access/data/K562_ChipSeq.csv
causalscbench/data_access/datasets/__init__.py
causalscbench/data_access/datasets/download_evaluation_files.py
causalscbench/data_access/datasets/download_weissmann.py
causalscbench/data_access/utils/__init__.py
causalscbench/data_access/utils/download.py
causalscbench/data_access/utils/preprocessing.py
causalscbench/data_access/utils/splitting.py
causalscbench/evaluation/__init__.py
causalscbench/evaluation/biological_evaluation.py
causalscbench/evaluation/statistical_evaluation.py
causalscbench/models/__init__.py
causalscbench/models/abstract_model.py
causalscbench/models/arboreto_baselines.py
causalscbench/models/causallearn_models.py
causalscbench/models/dcdi_models.py
causalscbench/models/feature_selection.py
causalscbench/models/gies.py
causalscbench/models/notears.py
causalscbench/models/random_network.py
causalscbench/models/sparsest_permutations.py
causalscbench/models/training_regimes.py
causalscbench/models/varsortability.py
causalscbench/models/utils/__init__.py
causalscbench/models/utils/model_utils.py
causalscbench/third_party/__init__.py
causalscbench/third_party/causaldag/__init__.py
causalscbench/third_party/causaldag/ci_tests/__init__.py
causalscbench/third_party/causaldag/ci_tests/parametric/__init__.py
causalscbench/third_party/causaldag/ci_tests/parametric/partial_correlation_test.py
causalscbench/third_party/dcdfg/__init__.py
causalscbench/third_party/dcdfg/dcdfg/__init__.py
causalscbench/third_party/dcdfg/dcdfg/callback.py
causalbench-1.1.2.dist-info/LICENSE.txt
causalbench-1.1.2.dist-info/METADATA
causalbench-1.1.2.dist-info/WHEEL
causalbench-1.1.2.dist-info/entry_points.txt
causalbench-1.1.2.dist-info/top_level.txt
causalbench-1.1.2.dist-info/RECORD
