Metadata-Version: 2.1
Name: causalbench
Version: 1.1.2
Home-page: https://www.gsk.ai/causalbenchchallenge
Author: see README.txt
Author-email: biomedical-ai-external@gsk.com
License: Apache-2.0
Classifier: Programming Language :: Python :: 3
Classifier: License :: OSI Approved :: Apache Software License
Classifier: Operating System :: OS Independent
Requires-Python: >=3.8
License-File: LICENSE.txt
Requires-Dist: arboreto
Requires-Dist: cdt
Requires-Dist: distributed
Requires-Dist: gdown
Requires-Dist: json5
Requires-Dist: networkx
Requires-Dist: numpy
Requires-Dist: pandas
Requires-Dist: scikit-learn
Requires-Dist: scipy
Requires-Dist: seaborn
Requires-Dist: torch
Requires-Dist: torchvision
Requires-Dist: tqdm
Requires-Dist: magic-impute
Requires-Dist: openpyxl
Requires-Dist: pytorch-lightning
Requires-Dist: setuptools
Requires-Dist: scprep
Requires-Dist: scanpy
Requires-Dist: slingpy
Requires-Dist: causal-learn
Requires-Dist: causaldag
Requires-Dist: python-igraph
Requires-Dist: gies
Requires-Dist: black ~=22.3.0
Requires-Dist: pre-commit ~=2.19.0
Requires-Dist: pre-commit-hooks ~=4.2.0
Requires-Dist: isort ~=5.10.1
